{
  "title": "外卖100元肯德基，自己做能花多少钱？炸鸡翅和汉堡都不错 #美食  #肯德基  #美食趣胃计划",
  "author": "",
  "platform": "抖音",
  "platform_raw": "Douyin",
  "url": "https://www.douyin.com/video/6894813959476612363?previous_page=web_code_link",
  "original_url": "https://v.douyin.com/GsWljD5euLA/",
  "duration": 200,
  "description": "外卖100元肯德基，自己做能花多少钱？炸鸡翅和汉堡都不错 #美食  #肯德基  #美食趣胃计划",
  "thumbnail": "https://p5-sign.douyinpic.com/tos-cn-p-0015/cf4232d077494386ae263e923958a2f4_1605324014~tplv-dy-360p.jpeg?lk3s=138a59ce&x-expires=1782306000&x-signature=6tcsR6%2FrU7LdSa%2Fo2nlrxiwahjI%3D&from=327834062&s=PackSourceEnum_AWEME_DETAIL&se=false&sc=origin_cover&biz_tag=aweme_video&l=2026061021132595329E3970D7A7230C54",
  "tags": [],
  "mentions": [
    "@z.TL"
  ],
  "has_video": true,
  "has_audio": true,
  "has_transcript": true,
  "created_at": "2026-06-10T21:14:29.314464"
}